{"formJson":{"id":13,"uuid":"13de43ad-699a-41cf-83e6-62f26fe5264d","name":"Consent Form","version":"1","published":true,"auditInfo":{"creator":{"uuid":"c52d544a-7d55-11e5-acdf-90fba67c4298","display":"superman","links":[{"rel":"self","uri":"http://192.168.1.89/openmrs/ws/rest/v1/user/c52d544a-7d55-11e5-acdf-90fba67c4298"}]},"dateCreated":"2019-11-14T10:31:39.000+0600","changedBy":{"uuid":"c52d544a-7d55-11e5-acdf-90fba67c4298","display":"superman","links":[{"rel":"self","uri":"http://192.168.1.89/openmrs/ws/rest/v1/user/c52d544a-7d55-11e5-acdf-90fba67c4298"}]},"dateChanged":"2019-11-14T10:43:33.000+0600"},"resources":[{"value":"{\"name\":\"Consent Form\",\"uuid\":\"13de43ad-699a-41cf-83e6-62f26fe5264d\",\"defaultLocale\":\"en\",\"controls\":[{\"type\":\"section\",\"label\":{\"translationKey\":\"SECTION_1\",\"type\":\"label\",\"value\":\"Information Of Doctor\",\"id\":\"1\"},\"properties\":{\"location\":{\"column\":0,\"row\":0}},\"id\":\"1\",\"controls\":[{\"type\":\"obsControl\",\"label\":{\"translationKey\":\"DOCTORSNAME_2\",\"id\":\"2\",\"units\":\"\",\"type\":\"label\",\"value\":\"DoctorsName\"},\"properties\":{\"mandatory\":true,\"notes\":false,\"addMore\":false,\"hideLabel\":false,\"controlEvent\":false,\"location\":{\"column\":0,\"row\":0}},\"id\":\"2\",\"concept\":{\"name\":\"DoctorsName\",\"uuid\":\"f1390eaa-0697-11ea-8da7-08002719de0f\",\"datatype\":\"Text\",\"conceptClass\":\"Misc\",\"conceptHandler\":null,\"answers\":[],\"properties\":{\"allowDecimal\":null}},\"units\":null,\"hiNormal\":null,\"lowNormal\":null,\"hiAbsolute\":null,\"lowAbsolute\":null},{\"type\":\"obsControl\",\"label\":{\"translationKey\":\"ANESTHESIOLOGISTNAME_3\",\"id\":\"3\",\"units\":\"\",\"type\":\"label\",\"value\":\"AnesthesiologistName\"},\"properties\":{\"mandatory\":true,\"notes\":false,\"addMore\":false,\"hideLabel\":false,\"controlEvent\":false,\"location\":{\"column\":0,\"row\":1}},\"id\":\"3\",\"concept\":{\"name\":\"AnesthesiologistName\",\"uuid\":\"f13d121d-0697-11ea-8da7-08002719de0f\",\"datatype\":\"Text\",\"conceptClass\":\"Misc\",\"conceptHandler\":null,\"answers\":[],\"properties\":{\"allowDecimal\":null}},\"units\":null,\"hiNormal\":null,\"lowNormal\":null,\"hiAbsolute\":null,\"lowAbsolute\":null}]},{\"type\":\"section\",\"label\":{\"translationKey\":\"SECTION_4\",\"type\":\"label\",\"value\":\"Information Of Gurdian\",\"id\":\"4\"},\"properties\":{\"location\":{\"column\":0,\"row\":1}},\"id\":\"4\",\"controls\":[{\"type\":\"obsControl\",\"label\":{\"translationKey\":\"GUARDIANSNAME_5\",\"id\":\"5\",\"units\":\"\",\"type\":\"label\",\"value\":\"GuardiansName\"},\"properties\":{\"mandatory\":true,\"notes\":false,\"addMore\":false,\"hideLabel\":false,\"controlEvent\":false,\"location\":{\"column\":0,\"row\":0}},\"id\":\"5\",\"concept\":{\"name\":\"GuardiansName\",\"uuid\":\"f14099f1-0697-11ea-8da7-08002719de0f\",\"datatype\":\"Text\",\"conceptClass\":\"Misc\",\"conceptHandler\":null,\"answers\":[],\"properties\":{\"allowDecimal\":null}},\"units\":null,\"hiNormal\":null,\"lowNormal\":null,\"hiAbsolute\":null,\"lowAbsolute\":null},{\"type\":\"obsControl\",\"label\":{\"translationKey\":\"RELATIONWITHPATIENT_6\",\"id\":\"6\",\"units\":\"\",\"type\":\"label\",\"value\":\"RelationWithPatient\"},\"properties\":{\"mandatory\":true,\"notes\":false,\"addMore\":false,\"hideLabel\":false,\"controlEvent\":false,\"location\":{\"column\":0,\"row\":1}},\"id\":\"6\",\"concept\":{\"name\":\"RelationWithPatient\",\"uuid\":\"f143c6c1-0697-11ea-8da7-08002719de0f\",\"datatype\":\"Text\",\"conceptClass\":\"Misc\",\"conceptHandler\":null,\"answers\":[],\"properties\":{\"allowDecimal\":null}},\"units\":null,\"hiNormal\":null,\"lowNormal\":null,\"hiAbsolute\":null,\"lowAbsolute\":null},{\"type\":\"obsControl\",\"label\":{\"translationKey\":\"GUARDIANSADDRESS_7\",\"id\":\"7\",\"units\":\"\",\"type\":\"label\",\"value\":\"GuardiansAddress\"},\"properties\":{\"mandatory\":false,\"notes\":false,\"addMore\":false,\"hideLabel\":false,\"controlEvent\":false,\"location\":{\"column\":0,\"row\":2}},\"id\":\"7\",\"concept\":{\"name\":\"GuardiansAddress\",\"uuid\":\"f146b557-0697-11ea-8da7-08002719de0f\",\"datatype\":\"Text\",\"conceptClass\":\"Misc\",\"conceptHandler\":null,\"answers\":[],\"properties\":{\"allowDecimal\":null}},\"units\":null,\"hiNormal\":null,\"lowNormal\":null,\"hiAbsolute\":null,\"lowAbsolute\":null},{\"type\":\"obsControl\",\"label\":{\"translationKey\":\"GUARDIANSPHONENO_8\",\"id\":\"8\",\"units\":\"\",\"type\":\"label\",\"value\":\"GuardiansPhoneNo\"},\"properties\":{\"mandatory\":true,\"notes\":false,\"addMore\":false,\"hideLabel\":false,\"controlEvent\":false,\"location\":{\"column\":0,\"row\":3}},\"id\":\"8\",\"concept\":{\"name\":\"GuardiansPhoneNo\",\"uuid\":\"f149eff9-0697-11ea-8da7-08002719de0f\",\"datatype\":\"Text\",\"conceptClass\":\"Misc\",\"conceptHandler\":null,\"answers\":[],\"properties\":{\"allowDecimal\":null}},\"units\":null,\"hiNormal\":null,\"lowNormal\":null,\"hiAbsolute\":null,\"lowAbsolute\":null}]},{\"type\":\"section\",\"label\":{\"translationKey\":\"SECTION_9\",\"type\":\"label\",\"value\":\"Information Of Witness\",\"id\":\"9\"},\"properties\":{\"location\":{\"column\":0,\"row\":2}},\"id\":\"9\",\"controls\":[{\"type\":\"obsControl\",\"label\":{\"translationKey\":\"WITNESSNAME_10\",\"id\":\"10\",\"units\":\"\",\"type\":\"label\",\"value\":\"WitnessName\"},\"properties\":{\"mandatory\":false,\"notes\":false,\"addMore\":false,\"hideLabel\":false,\"controlEvent\":false,\"location\":{\"column\":0,\"row\":0}},\"id\":\"10\",\"concept\":{\"name\":\"WitnessName\",\"uuid\":\"f152f79f-0697-11ea-8da7-08002719de0f\",\"datatype\":\"Text\",\"conceptClass\":\"Misc\",\"conceptHandler\":null,\"answers\":[],\"properties\":{\"allowDecimal\":null}},\"units\":null,\"hiNormal\":null,\"lowNormal\":null,\"hiAbsolute\":null,\"lowAbsolute\":null},{\"type\":\"obsControl\",\"label\":{\"translationKey\":\"WITNESSADDRESS_11\",\"id\":\"11\",\"units\":\"\",\"type\":\"label\",\"value\":\"WitnessAddress\"},\"properties\":{\"mandatory\":false,\"notes\":false,\"addMore\":false,\"hideLabel\":false,\"controlEvent\":false,\"location\":{\"column\":0,\"row\":1}},\"id\":\"11\",\"concept\":{\"name\":\"WitnessAddress\",\"uuid\":\"f15637c4-0697-11ea-8da7-08002719de0f\",\"datatype\":\"Text\",\"conceptClass\":\"Misc\",\"conceptHandler\":null,\"answers\":[],\"properties\":{\"allowDecimal\":null}},\"units\":null,\"hiNormal\":null,\"lowNormal\":null,\"hiAbsolute\":null,\"lowAbsolute\":null},{\"type\":\"obsControl\",\"label\":{\"translationKey\":\"WITNESSPHONENO_12\",\"id\":\"12\",\"units\":\"\",\"type\":\"label\",\"value\":\"WitnessPhoneNo\"},\"properties\":{\"mandatory\":false,\"notes\":false,\"addMore\":false,\"hideLabel\":false,\"controlEvent\":false,\"location\":{\"column\":0,\"row\":2}},\"id\":\"12\",\"concept\":{\"name\":\"WitnessPhoneNo\",\"uuid\":\"f159aec6-0697-11ea-8da7-08002719de0f\",\"datatype\":\"Text\",\"conceptClass\":\"Misc\",\"conceptHandler\":null,\"answers\":[],\"properties\":{\"allowDecimal\":null}},\"units\":null,\"hiNormal\":null,\"lowNormal\":null,\"hiAbsolute\":null,\"lowAbsolute\":null}]}],\"events\":{},\"translationsUrl\":\"/openmrs/ws/rest/v1/bahmniie/form/translations\"}","dataType":"org.bahmni.customdatatype.datatype.FileSystemStorageDatatype","uuid":"51dfda63-d468-4be5-906f-fd71596358e3"}]},"translations":[{"locale":"en","labels":{"SECTION_1":"Information Of Doctor","SECTION_4":"Information Of Gurdian","SECTION_9":"Information Of Witness"},"concepts":{"RELATIONWITHPATIENT_6":"Relation with patient","WITNESSPHONENO_12":"Phone No.","WITNESSADDRESS_11":"Address","WITNESSNAME_10":"Name","ANESTHESIOLOGISTNAME_3":"Anesthesiologist Name","DOCTORSNAME_2":"Name","GUARDIANSPHONENO_8":"Phone No.","GUARDIANSNAME_5":"Name","GUARDIANSADDRESS_7":"Address"},"formName":"Consent Form","version":"1"}]}